netbox_secrets/__init__.py
netbox_secrets/constants.py
netbox_secrets/exceptions.py
netbox_secrets/filtersets.py
netbox_secrets/hashers.py
netbox_secrets/navigation.py
netbox_secrets/querysets.py
netbox_secrets/signals.py
netbox_secrets/tables.py
netbox_secrets/template_content.py
netbox_secrets/urls.py
netbox_secrets/views.py
netbox_secrets/api/__init__.py
netbox_secrets/api/serializers.py
netbox_secrets/api/urls.py
netbox_secrets/api/views.py
netbox_secrets/forms/__init__.py
netbox_secrets/forms/bulk_edit.py
netbox_secrets/forms/bulk_import.py
netbox_secrets/forms/filterset.py
netbox_secrets/forms/model_forms.py
netbox_secrets/graphql/__init__.py
netbox_secrets/graphql/filters.py
netbox_secrets/graphql/schema.py
netbox_secrets/graphql/types.py
netbox_secrets/migrations/0001_initial.py
netbox_secrets/migrations/0002_populate_userkeys.py
netbox_secrets/migrations/0003_populate_secretroles.py
netbox_secrets/migrations/0004_populate_secrets.py
netbox_secrets/migrations/0005_alter_secret_custom_field_data_and_more.py
netbox_secrets/migrations/0006_alter_userkey_created_alter_userkey_last_updated.py
netbox_secrets/migrations/0007_secret__object_repr_secret_comments_and_more.py
netbox_secrets/migrations/0008_userkey_custom_field_data_userkey_tags.py
netbox_secrets/migrations/__init__.py
netbox_secrets/models/__init__.py
netbox_secrets/models/secrets.py
netbox_secrets/static/netbox_secrets/secrets.js
netbox_secrets/static/netbox_secrets/secrets.js.map
netbox_secrets/templates/netbox_secrets/activate_keys.html
netbox_secrets/templates/netbox_secrets/secret.html
netbox_secrets/templates/netbox_secrets/secret_edit.html
netbox_secrets/templates/netbox_secrets/secretrole.html
netbox_secrets/templates/netbox_secrets/userkey.html
netbox_secrets/templates/netbox_secrets/userkey_edit.html
netbox_secrets/templates/netbox_secrets/userkey_list.html
netbox_secrets/templates/netbox_secrets/inc/private_key_modal.html
netbox_secrets/templates/netbox_secrets/inc/secret_actions.html
netbox_secrets-2.4.2.dist-info/licenses/LICENSE.md
netbox_secrets-2.4.2.dist-info/METADATA
netbox_secrets-2.4.2.dist-info/WHEEL
netbox_secrets-2.4.2.dist-info/top_level.txt
netbox_secrets-2.4.2.dist-info/RECORD
