Metadata-Version: 2.4
Name: netbox-secrets
Version: 2.4.2
Summary: Enhance your secret management with encrypted storage and flexible, user-friendly features.
Home-page: https://github.com/Onemind-Services-LLC/netbox-secrets/
Author: Abhimanyu Saharan
Author-email: asaharan@onemindservices.com
Maintainer: Prince Kumar
Maintainer-email: pkumar@onemindservices.com
License: Apache 2.0
Classifier: Programming Language :: Python :: 3
Classifier: License :: OSI Approved :: Apache Software License
Classifier: Operating System :: OS Independent
Requires-Python: >=3.10
License-File: LICENSE.md
Requires-Dist: pycryptodome==3.23.0
Dynamic: author
Dynamic: author-email
Dynamic: classifier
Dynamic: description
Dynamic: description-content-type
Dynamic: home-page
Dynamic: license
Dynamic: license-file
Dynamic: maintainer
Dynamic: maintainer-email
Dynamic: requires-dist
Dynamic: requires-python
Dynamic: summary
